README.rst
setup.py
macht/__init__.py
macht/__main__.py
macht/grid.py
macht/save.py
macht/tile.py
macht.egg-info/PKG-INFO
macht.egg-info/SOURCES.txt
macht.egg-info/dependency_links.txt
macht.egg-info/entry_points.txt
macht.egg-info/requires.txt
macht.egg-info/top_level.txt
macht/term/__init__.py
macht/term/__main__.py
macht/term/grid.py
macht/term/main.py
macht/term/tile.py