Metadata-Version: 1.1
Name: macht
Version: 0.1.5
Summary: A 2048 clone in python with Terminal UI
Home-page: https://github.com/polyphemus/macht
Author: Rolf Morel
Author-email: rolfmorel@gmail.com
License: LGPLv3
Keywords: 2048,terminal,game,board,puzzle,tiles
Platform: UNKNOWN
Classifier: Environment :: Console
Classifier: Intended Audience :: End Users/Desktop
Classifier: License :: OSI Approved :: GNU Lesser General Public License v3 or later (LGPLv3+)
Classifier: Operating System :: POSIX
Classifier: Programming Language :: Python :: 2
Classifier: Programming Language :: Python :: 2.6
Classifier: Programming Language :: Python :: 2.7
Classifier: Programming Language :: Python :: 3
Classifier: Programming Language :: Python :: 3.2
Classifier: Programming Language :: Python :: 3.3
Classifier: Topic :: Games/Entertainment :: Puzzle Games
Classifier: Topic :: Terminals
